spell/__init__.py
spell/spell.py
spellpy/__init__.py
spellpy/spell.py
spellpy/spellpy.py
tests/__init__.py
tests/test_spell.py
tests/test_spellpy.py
spellpy-0.0.9.dist-info/LICENSE
spellpy-0.0.9.dist-info/METADATA
spellpy-0.0.9.dist-info/WHEEL
spellpy-0.0.9.dist-info/top_level.txt
spellpy-0.0.9.dist-info/RECORD
