Metadata-Version: 2.1
Name: spellpy
Version: 0.0.9
Summary: Auto parser for system raw log without human guidance
Home-page: https://github.com/nailo2c/spellpy
Author: nailo2c
Author-email: nailo2c@gmail.com
License: UNKNOWN
Platform: UNKNOWN
Classifier: Programming Language :: Python :: 3
Classifier: License :: OSI Approved :: MIT License
Classifier: Operating System :: OS Independent
Requires-Python: >=3.6
Requires-Dist: pandas
